texting_robots/__init__.py
texting_robots/__init__.pyi
texting_robots/py.typed
texting_robots/texting_robots.cpython-311-aarch64-linux-gnu.so
texting_robots_py-0.2.2.dist-info/METADATA
texting_robots_py-0.2.2.dist-info/WHEEL
texting_robots_py-0.2.2.dist-info/licenses/LICENSE.Apache-2.0
texting_robots_py-0.2.2.dist-info/licenses/LICENSE.MIT
texting_robots_py-0.2.2.dist-info/RECORD
