Metadata-Version: 2.4
Name: texting-robots-py
Version: 0.2.2
Classifier: Programming Language :: Rust
Classifier: Programming Language :: Python :: Implementation :: CPython
Classifier: Programming Language :: Python :: Implementation :: PyPy
License-File: LICENSE.Apache-2.0
License-File: LICENSE.MIT
Summary: Python binding for Texting Robots
License: MIT OR Apache-2.0
Requires-Python: >=3.8
Project-URL: Source Code, https://github.com/benwebber/texting-robots-py
